<settings>
  <servers>
    <server>
      <id>sonatype-nexus-snapshots</id>
      <username>${env.SONATYPE_USER}</username>
      <password>${env.SONATYPE_PASS}</password>
    </server>
  </servers>
  <profiles>
    <profile>
      <id>snapshot-repo</id>
      <repositories>
        <repository>
          <id>sonatype-nexus-snapshots</id>
          <url>https://oss.sonatype.org/content/repositories/snapshots</url>
          <releases>
            <enabled>false</enabled>
          </releases>
          <snapshots>
            <enabled>true</enabled>
          </snapshots>
        </repository>
      </repositories>
      <pluginRepositories>
        <pluginRepository>
          <id>sonatype-nexus-snapshots</id>
          <url>https://oss.sonatype.org/content/repositories/snapshots</url>
          <releases>
            <enabled>false</enabled>
          </releases>
          <snapshots>
            <enabled>true</enabled>
          </snapshots>
        </pluginRepository>
      </pluginRepositories>
    </profile>
  </profiles>
  <activeProfiles>
    <activeProfile>snapshot-repo</activeProfile>
  </activeProfiles>
</settings>